<?xml version="1.0" encoding="UTF-8"?>
<Tokens version="1.0">
	<File path="Protocols/AlfrescoSession.html">
		
		<Token>
			<TokenIdentifier>//apple_ref/occ/intf/AlfrescoSession</TokenIdentifier>
			<Abstract type="html">The AlfrescoSession category defines the properties made available for a session to an Alfresco repository.</Abstract>
			<DeclaredIn>AlfrescoSession.h</DeclaredIn>
			
			<NodeRef refid="33"/>
		</Token>
		
		
		<Token>
			<TokenIdentifier>//apple_ref/occ/intfm/AlfrescoSession/setPersonIdentifier:</TokenIdentifier>
			<Abstract type="html">The currently authenticated user.</Abstract>
			<DeclaredIn>AlfrescoSession.h</DeclaredIn>			
			
			<Declaration>@property (nonatomic, strong, readonly) NSString *personIdentifier</Declaration>
			
			
			<Anchor>//api/name/personIdentifier</Anchor>
		</Token>
		
		<Token>
			<TokenIdentifier>//apple_ref/occ/intfp/AlfrescoSession/personIdentifier</TokenIdentifier>
			<Abstract type="html">The currently authenticated user.</Abstract>
			<DeclaredIn>AlfrescoSession.h</DeclaredIn>			
			
			<Declaration>@property (nonatomic, strong, readonly) NSString *personIdentifier</Declaration>
			
			
			<Anchor>//api/name/personIdentifier</Anchor>
		</Token>
		
		<Token>
			<TokenIdentifier>//apple_ref/occ/intfm/AlfrescoSession/setRepositoryInfo:</TokenIdentifier>
			<Abstract type="html">Information describing the repository the session is connected to.</Abstract>
			<DeclaredIn>AlfrescoSession.h</DeclaredIn>			
			
			<Declaration>@property (nonatomic, strong, readonly) AlfrescoRepositoryInfo *repositoryInfo</Declaration>
			
			
			<Anchor>//api/name/repositoryInfo</Anchor>
		</Token>
		
		<Token>
			<TokenIdentifier>//apple_ref/occ/intfp/AlfrescoSession/repositoryInfo</TokenIdentifier>
			<Abstract type="html">Information describing the repository the session is connected to.</Abstract>
			<DeclaredIn>AlfrescoSession.h</DeclaredIn>			
			
			<Declaration>@property (nonatomic, strong, readonly) AlfrescoRepositoryInfo *repositoryInfo</Declaration>
			
			
			<Anchor>//api/name/repositoryInfo</Anchor>
		</Token>
		
		<Token>
			<TokenIdentifier>//apple_ref/occ/intfm/AlfrescoSession/setBaseUrl:</TokenIdentifier>
			<Abstract type="html">The base URL of the repository.</Abstract>
			<DeclaredIn>AlfrescoSession.h</DeclaredIn>			
			
			<Declaration>@property (nonatomic, strong, readonly) NSURL *baseUrl</Declaration>
			
			
			<Anchor>//api/name/baseUrl</Anchor>
		</Token>
		
		<Token>
			<TokenIdentifier>//apple_ref/occ/intfp/AlfrescoSession/baseUrl</TokenIdentifier>
			<Abstract type="html">The base URL of the repository.</Abstract>
			<DeclaredIn>AlfrescoSession.h</DeclaredIn>			
			
			<Declaration>@property (nonatomic, strong, readonly) NSURL *baseUrl</Declaration>
			
			
			<Anchor>//api/name/baseUrl</Anchor>
		</Token>
		
		<Token>
			<TokenIdentifier>//apple_ref/occ/intfm/AlfrescoSession/setRootFolder:</TokenIdentifier>
			<Abstract type="html">The root folder of the repository.</Abstract>
			<DeclaredIn>AlfrescoSession.h</DeclaredIn>			
			
			<Declaration>@property (nonatomic, strong, readonly) AlfrescoFolder *rootFolder</Declaration>
			
			
			<Anchor>//api/name/rootFolder</Anchor>
		</Token>
		
		<Token>
			<TokenIdentifier>//apple_ref/occ/intfp/AlfrescoSession/rootFolder</TokenIdentifier>
			<Abstract type="html">The root folder of the repository.</Abstract>
			<DeclaredIn>AlfrescoSession.h</DeclaredIn>			
			
			<Declaration>@property (nonatomic, strong, readonly) AlfrescoFolder *rootFolder</Declaration>
			
			
			<Anchor>//api/name/rootFolder</Anchor>
		</Token>
		
		<Token>
			<TokenIdentifier>//apple_ref/occ/intfm/AlfrescoSession/setDefaultListingContext:</TokenIdentifier>
			<Abstract type="html">a default listing context for the session</Abstract>
			<DeclaredIn>AlfrescoSession.h</DeclaredIn>			
			
			<Declaration>@property (nonatomic, strong, readonly) AlfrescoListingContext *defaultListingContext</Declaration>
			
			
			<Anchor>//api/name/defaultListingContext</Anchor>
		</Token>
		
		<Token>
			<TokenIdentifier>//apple_ref/occ/intfp/AlfrescoSession/defaultListingContext</TokenIdentifier>
			<Abstract type="html">a default listing context for the session</Abstract>
			<DeclaredIn>AlfrescoSession.h</DeclaredIn>			
			
			<Declaration>@property (nonatomic, strong, readonly) AlfrescoListingContext *defaultListingContext</Declaration>
			
			
			<Anchor>//api/name/defaultListingContext</Anchor>
		</Token>
		
		<Token>
			<TokenIdentifier>//apple_ref/occ/intfm/AlfrescoSession/allParameterKeys</TokenIdentifier>
			<Abstract type="html">Gives back all keys of the session data dictionary.</Abstract>
			<DeclaredIn>AlfrescoSession.h</DeclaredIn>			
			
			<Declaration>- (NSArray *)allParameterKeys</Declaration>
			
			<ReturnValue><Abstract type="html">All keys of the session data dictionary.</Abstract></ReturnValue>
			<Anchor>//api/name/allParameterKeys</Anchor>
		</Token>
		
		<Token>
			<TokenIdentifier>//apple_ref/occ/intfm/AlfrescoSession/objectForParameter:</TokenIdentifier>
			<Abstract type="html">Gets a session data value for a specific key.</Abstract>
			<DeclaredIn>AlfrescoSession.h</DeclaredIn>			
			
			<Declaration>- (id)objectForParameter:(id)key</Declaration>
			<Parameters>
				<Parameter>
					<Name>key</Name>
					<Abstract type="html">The key for the object to be retrieved.</Abstract>
				</Parameter>
			</Parameters>
			<ReturnValue><Abstract type="html">Session data value.</Abstract></ReturnValue>
			<Anchor>//api/name/objectForParameter:</Anchor>
		</Token>
		
		<Token>
			<TokenIdentifier>//apple_ref/occ/intfm/AlfrescoSession/setObject:forParameter:</TokenIdentifier>
			<Abstract type="html">Adds an object to the session data.</Abstract>
			<DeclaredIn>AlfrescoSession.h</DeclaredIn>			
			
			<Declaration>- (void)setObject:(id)object forParameter:(id)key</Declaration>
			<Parameters>
				<Parameter>
					<Name>object</Name>
					<Abstract type="html">The object to be added.</Abstract>
				</Parameter><Parameter>
					<Name>key</Name>
					<Abstract type="html">The key for the object to be added.</Abstract>
				</Parameter>
			</Parameters>
			
			<Anchor>//api/name/setObject:forParameter:</Anchor>
		</Token>
		
		<Token>
			<TokenIdentifier>//apple_ref/occ/intfm/AlfrescoSession/addParametersFromDictionary:</TokenIdentifier>
			<Abstract type="html">Adds an dictionary of objects to the session data.</Abstract>
			<DeclaredIn>AlfrescoSession.h</DeclaredIn>			
			
			<Declaration>- (void)addParametersFromDictionary:(NSDictionary *)dictionary</Declaration>
			<Parameters>
				<Parameter>
					<Name>dictionary</Name>
					<Abstract type="html">The dictionary of objects to be added.</Abstract>
				</Parameter>
			</Parameters>
			
			<Anchor>//api/name/addParametersFromDictionary:</Anchor>
		</Token>
		
		<Token>
			<TokenIdentifier>//apple_ref/occ/intfm/AlfrescoSession/removeParameter:</TokenIdentifier>
			<Abstract type="html">Removes a session data entry.</Abstract>
			<DeclaredIn>AlfrescoSession.h</DeclaredIn>			
			
			<Declaration>- (void)removeParameter:(id)key</Declaration>
			<Parameters>
				<Parameter>
					<Name>key</Name>
					<Abstract type="html">The key for the object to be removed.</Abstract>
				</Parameter>
			</Parameters>
			
			<Anchor>//api/name/removeParameter:</Anchor>
		</Token>
		
	</File>
</Tokens>