<?xml version="1.0" encoding="UTF-8"?>
<Tokens version="1.0">
	<File path="Classes/AlfrescoSiteService.html">
		
		<Token>
			<TokenIdentifier>//apple_ref/occ/cl/AlfrescoSiteService</TokenIdentifier>
			<Abstract type="html">The AlfrescoSiteService provides various ways to retrieve sites from an Alfresco repository.</Abstract>
			<DeclaredIn>AlfrescoSiteService.h</DeclaredIn>
			
			<NodeRef refid="29"/>
		</Token>
		
		
		<Token>
			<TokenIdentifier>//apple_ref/occ/instm/AlfrescoSiteService/initWithSession:</TokenIdentifier>
			<Abstract type="html">Initialises with a standard Cloud or OnPremise session</Abstract>
			<DeclaredIn>AlfrescoSiteService.h</DeclaredIn>			
			
			<Declaration>- (id)initWithSession:(id&lt;AlfrescoSession&gt;)session</Declaration>
			<Parameters>
				<Parameter>
					<Name>session</Name>
					<Abstract type="html">the AlfrescoSession to initialise the site service with.</Abstract>
				</Parameter>
			</Parameters>
			
			<Anchor>//api/name/initWithSession:</Anchor>
		</Token>
		
		<Token>
			<TokenIdentifier>//apple_ref/occ/instm/AlfrescoSiteService/retrieveAllSitesWithCompletionBlock:</TokenIdentifier>
			<Abstract type="html">Retrieves all the sites in the repository.</Abstract>
			<DeclaredIn>AlfrescoSiteService.h</DeclaredIn>			
			
			<Declaration>- (void)retrieveAllSitesWithCompletionBlock:(AlfrescoArrayCompletionBlock)completionBlock</Declaration>
			<Parameters>
				<Parameter>
					<Name>completionBlock</Name>
					<Abstract type="html">The block that&apos;s called with the retrieved sites in case the operation succeeds.</Abstract>
				</Parameter>
			</Parameters>
			
			<Anchor>//api/name/retrieveAllSitesWithCompletionBlock:</Anchor>
		</Token>
		
		<Token>
			<TokenIdentifier>//apple_ref/occ/instm/AlfrescoSiteService/retrieveAllSitesWithListingContext:completionBlock:</TokenIdentifier>
			<Abstract type="html">Retrieves sites in the repository with listing context.</Abstract>
			<DeclaredIn>AlfrescoSiteService.h</DeclaredIn>			
			
			<Declaration>- (void)retrieveAllSitesWithListingContext:(AlfrescoListingContext *)listingContext completionBlock:(AlfrescoPagingResultCompletionBlock)completionBlock</Declaration>
			<Parameters>
				<Parameter>
					<Name>listingContext</Name>
					<Abstract type="html">The listing context with a paging definition that&apos;s used to retrieve the nodes.</Abstract>
				</Parameter><Parameter>
					<Name>completionBlock</Name>
					<Abstract type="html">The block that&apos;s called with the retrieved sites in case the operation succeeds.</Abstract>
				</Parameter>
			</Parameters>
			
			<Anchor>//api/name/retrieveAllSitesWithListingContext:completionBlock:</Anchor>
		</Token>
		
		<Token>
			<TokenIdentifier>//apple_ref/occ/instm/AlfrescoSiteService/retrieveSitesWithCompletionBlock:</TokenIdentifier>
			<Abstract type="html">Retrieves all the sites for the current user of the session.</Abstract>
			<DeclaredIn>AlfrescoSiteService.h</DeclaredIn>			
			
			<Declaration>- (void)retrieveSitesWithCompletionBlock:(AlfrescoArrayCompletionBlock)completionBlock</Declaration>
			<Parameters>
				<Parameter>
					<Name>completionBlock</Name>
					<Abstract type="html">The block that&apos;s called with the retrieved sites in case the operation succeeds.</Abstract>
				</Parameter>
			</Parameters>
			
			<Anchor>//api/name/retrieveSitesWithCompletionBlock:</Anchor>
		</Token>
		
		<Token>
			<TokenIdentifier>//apple_ref/occ/instm/AlfrescoSiteService/retrieveSitesWithListingContext:completionBlock:</TokenIdentifier>
			<Abstract type="html">Retrieves the sites for the current session user with listing context.</Abstract>
			<DeclaredIn>AlfrescoSiteService.h</DeclaredIn>			
			
			<Declaration>- (void)retrieveSitesWithListingContext:(AlfrescoListingContext *)listingContext completionBlock:(AlfrescoPagingResultCompletionBlock)completionBlock</Declaration>
			<Parameters>
				<Parameter>
					<Name>listingContext</Name>
					<Abstract type="html">The listing context with a paging definition that&apos;s used to retrieve the nodes.</Abstract>
				</Parameter><Parameter>
					<Name>completionBlock</Name>
					<Abstract type="html">The block that&apos;s called with the retrieved sites in case the operation succeeds.</Abstract>
				</Parameter>
			</Parameters>
			
			<Anchor>//api/name/retrieveSitesWithListingContext:completionBlock:</Anchor>
		</Token>
		
		<Token>
			<TokenIdentifier>//apple_ref/occ/instm/AlfrescoSiteService/retrieveFavoriteSitesWithCompletionBlock:</TokenIdentifier>
			<Abstract type="html">Retrieves all the favorite sites for the current session user.</Abstract>
			<DeclaredIn>AlfrescoSiteService.h</DeclaredIn>			
			
			<Declaration>- (void)retrieveFavoriteSitesWithCompletionBlock:(AlfrescoArrayCompletionBlock)completionBlock</Declaration>
			<Parameters>
				<Parameter>
					<Name>completionBlock</Name>
					<Abstract type="html">The block that&apos;s called with the retrieved sites in case the operation succeeds.</Abstract>
				</Parameter>
			</Parameters>
			
			<Anchor>//api/name/retrieveFavoriteSitesWithCompletionBlock:</Anchor>
		</Token>
		
		<Token>
			<TokenIdentifier>//apple_ref/occ/instm/AlfrescoSiteService/retrieveFavoriteSitesWithListingContext:completionBlock:</TokenIdentifier>
			<Abstract type="html">Retrieves the favorite sites for the current session user with listing context.</Abstract>
			<DeclaredIn>AlfrescoSiteService.h</DeclaredIn>			
			
			<Declaration>- (void)retrieveFavoriteSitesWithListingContext:(AlfrescoListingContext *)listingContext completionBlock:(AlfrescoPagingResultCompletionBlock)completionBlock</Declaration>
			<Parameters>
				<Parameter>
					<Name>listingContext</Name>
					<Abstract type="html">The listing context with a paging definition that&apos;s used to retrieve the nodes.</Abstract>
				</Parameter><Parameter>
					<Name>completionBlock</Name>
					<Abstract type="html">The block that&apos;s called with the retrieved sites in case the operation succeeds.</Abstract>
				</Parameter>
			</Parameters>
			
			<Anchor>//api/name/retrieveFavoriteSitesWithListingContext:completionBlock:</Anchor>
		</Token>
		
		<Token>
			<TokenIdentifier>//apple_ref/occ/instm/AlfrescoSiteService/retrieveSiteWithShortName:completionBlock:</TokenIdentifier>
			<Abstract type="html">Retrieves a site with the given short name, if the site doesn’t exist nil is returned.</Abstract>
			<DeclaredIn>AlfrescoSiteService.h</DeclaredIn>			
			
			<Declaration>- (void)retrieveSiteWithShortName:(NSString *)siteShortName completionBlock:(AlfrescoSiteCompletionBlock)completionBlock</Declaration>
			<Parameters>
				<Parameter>
					<Name>siteShortName</Name>
					<Abstract type="html">The short name of the site that needs to be retrieved.</Abstract>
				</Parameter><Parameter>
					<Name>completionBlock</Name>
					<Abstract type="html">The block that&apos;s called with the retrieved site in case the operation succeeds.</Abstract>
				</Parameter>
			</Parameters>
			
			<Anchor>//api/name/retrieveSiteWithShortName:completionBlock:</Anchor>
		</Token>
		
		<Token>
			<TokenIdentifier>//apple_ref/occ/instm/AlfrescoSiteService/retrieveDocumentLibraryFolderForSite:completionBlock:</TokenIdentifier>
			<Abstract type="html">Retrieves the folder that represents the root of the Document Library for the site with the given short name.</Abstract>
			<DeclaredIn>AlfrescoSiteService.h</DeclaredIn>			
			
			<Declaration>- (void)retrieveDocumentLibraryFolderForSite:(NSString *)siteShortName completionBlock:(AlfrescoFolderCompletionBlock)completionBlock</Declaration>
			<Parameters>
				<Parameter>
					<Name>siteShortName</Name>
					<Abstract type="html">The short name of the site for which the document library needs to be retrieved.</Abstract>
				</Parameter><Parameter>
					<Name>completionBlock</Name>
					<Abstract type="html">The block that&apos;s called with the retrieved document library folder in case the operation succeeds.</Abstract>
				</Parameter>
			</Parameters>
			
			<Anchor>//api/name/retrieveDocumentLibraryFolderForSite:completionBlock:</Anchor>
		</Token>
		
	</File>
</Tokens>